{"SURVIVAL":{"armorContents":{"3":{"==":"org.bukkit.inventory.ItemStack","v":2730,"type":"DRAGON_HEAD"}},"enderChestContents":{},"offHandItem":{"==":"org.bukkit.inventory.ItemStack","v":2730,"type":"AIR","amount":0},"potions":[{"==":"PotionEffect","effect":1,"duration":307,"amplifier":0,"ambient":true,"has-particles":true,"has-icon":true},{"==":"PotionEffect","effect":10,"duration":307,"amplifier":0,"ambient":true,"has-particles":true,"has-icon":true}],"inventoryContents":{"22":{"==":"org.bukkit.inventory.ItemStack","v":2730,"type":"DIORITE","amount":5},"23":{"==":"org.bukkit.inventory.ItemStack","v":2730,"type":"BLACK_CONCRETE"},"24":{"==":"org.bukkit.inventory.ItemStack","v":2730,"type":"CUT_SANDSTONE_SLAB"},"25":{"==":"org.bukkit.inventory.ItemStack","v":2730,"type":"WARPED_PLANKS"},"26":{"==":"org.bukkit.inventory.ItemStack","v":2730,"type":"CUT_SANDSTONE"},"27":{"==":"org.bukkit.inventory.ItemStack","v":2730,"type":"SANDSTONE_STAIRS"},"28":{"==":"org.bukkit.inventory.ItemStack","v":2730,"type":"COAL","amount":6},"29":{"==":"org.bukkit.inventory.ItemStack","v":2730,"type":"COBBLESTONE","amount":16},"30":{"==":"org.bukkit.inventory.ItemStack","v":2730,"type":"POTION","meta":{"==":"ItemMeta","meta-type":"POTION","potion-type":"minecraft:healing"}},"31":{"==":"org.bukkit.inventory.ItemStack","v":2730,"type":"REDSTONE"},"10":{"==":"org.bukkit.inventory.ItemStack","v":2730,"type":"BLACK_CONCRETE"},"32":{"==":"org.bukkit.inventory.ItemStack","v":2730,"type":"STRING","amount":3},"11":{"==":"org.bukkit.inventory.ItemStack","v":2730,"type":"SNOW_BLOCK"},"33":{"==":"org.bukkit.inventory.ItemStack","v":2730,"type":"SPIDER_EYE","amount":2},"12":{"==":"org.bukkit.inventory.ItemStack","v":2730,"type":"BLUE_CONCRETE"},"34":{"==":"org.bukkit.inventory.ItemStack","v":2730,"type":"ARROW","amount":2},"13":{"==":"org.bukkit.inventory.ItemStack","v":2730,"type":"CHAIN"},"35":{"==":"org.bukkit.inventory.ItemStack","v":2730,"type":"GUNPOWDER","amount":2},"14":{"==":"org.bukkit.inventory.ItemStack","v":2730,"type":"IRON_TRAPDOOR"},"15":{"==":"org.bukkit.inventory.ItemStack","v":2730,"type":"BIRCH_TRAPDOOR"},"16":{"==":"org.bukkit.inventory.ItemStack","v":2730,"type":"DIORITE_WALL"},"17":{"==":"org.bukkit.inventory.ItemStack","v":2730,"type":"LIME_TERRACOTTA"},"39":{"==":"org.bukkit.inventory.ItemStack","v":2730,"type":"DRAGON_HEAD"},"18":{"==":"org.bukkit.inventory.ItemStack","v":2730,"type":"WHITE_CONCRETE"},"19":{"==":"org.bukkit.inventory.ItemStack","v":2730,"type":"LIME_CONCRETE"},"0":{"==":"org.bukkit.inventory.ItemStack","v":2730,"type":"WOODEN_AXE"},"1":{"==":"org.bukkit.inventory.ItemStack","v":2730,"type":"NETHERITE_SWORD","meta":{"==":"ItemMeta","meta-type":"UNSPECIFIC","Damage":2}},"2":{"==":"org.bukkit.inventory.ItemStack","v":2730,"type":"SPRUCE_SIGN","amount":2},"3":{"==":"org.bukkit.inventory.ItemStack","v":2730,"type":"LIGHT_GRAY_CONCRETE"},"4":{"==":"org.bukkit.inventory.ItemStack","v":2730,"type":"CONDUIT"},"5":{"==":"org.bukkit.inventory.ItemStack","v":2730,"type":"SMOOTH_STONE"},"6":{"==":"org.bukkit.inventory.ItemStack","v":2730,"type":"POLISHED_ANDESITE_STAIRS"},"7":{"==":"org.bukkit.inventory.ItemStack","v":2730,"type":"CYAN_TERRACOTTA"},"8":{"==":"org.bukkit.inventory.ItemStack","v":2730,"type":"REPEATING_COMMAND_BLOCK"},"9":{"==":"org.bukkit.inventory.ItemStack","v":2730,"type":"WHITE_CONCRETE_POWDER"},"20":{"==":"org.bukkit.inventory.ItemStack","v":2730,"type":"ROTTEN_FLESH","amount":5},"21":{"==":"org.bukkit.inventory.ItemStack","v":2730,"type":"WHITE_WOOL"}},"stats":{"ex":"1.05","ma":"300","fl":"17","el":"10","hp":"20.0","xp":"0.29629624","txp":"168","sa":"0.0","ft":"-20","fd":"0.0","ra":"300"}}}