{"SURVIVAL":{"inventoryContents":{},"potions":[{"==":"PotionEffect","effect":11,"duration":4615,"amplifier":0,"ambient":false,"has-particles":true,"has-icon":true},{"==":"PotionEffect","effect":22,"duration":1015,"amplifier":3,"ambient":false,"has-particles":true,"has-icon":true},{"==":"PotionEffect","effect":12,"duration":4615,"amplifier":0,"ambient":false,"has-particles":true,"has-icon":true}],"offHandItem":{"==":"org.bukkit.inventory.ItemStack","v":2580,"type":"AIR","amount":0},"armorContents":{},"enderChestContents":{},"stats":{"ex":"0.45601046","ma":"300","fl":"20","el":"0","hp":"20.0","xp":"0.0","txp":"0","ft":"-20","fd":"0.0","sa":"17.0","ra":"300"}}}