{"SURVIVAL":{"enderChestContents":{},"offHandItem":{"==":"org.bukkit.inventory.ItemStack","v":2580,"type":"AIR","amount":0},"armorContents":{},"potions":[],"inventoryContents":{"22":{"==":"org.bukkit.inventory.ItemStack","v":2580,"type":"STONE_BRICKS"},"23":{"==":"org.bukkit.inventory.ItemStack","v":2580,"type":"HAY_BLOCK"},"24":{"==":"org.bukkit.inventory.ItemStack","v":2580,"type":"DIRT"},"25":{"==":"org.bukkit.inventory.ItemStack","v":2580,"type":"GRASS_PATH"},"26":{"==":"org.bukkit.inventory.ItemStack","v":2580,"type":"PODZOL"},"27":{"==":"org.bukkit.inventory.ItemStack","v":2580,"type":"STONE_BUTTON"},"28":{"==":"org.bukkit.inventory.ItemStack","v":2580,"type":"REPEATER","amount":64},"29":{"==":"org.bukkit.inventory.ItemStack","v":2580,"type":"ACACIA_FENCE"},"30":{"==":"org.bukkit.inventory.ItemStack","v":2580,"type":"LANTERN"},"31":{"==":"org.bukkit.inventory.ItemStack","v":2580,"type":"ACACIA_STAIRS"},"10":{"==":"org.bukkit.inventory.ItemStack","v":2580,"type":"JUNGLE_STAIRS"},"32":{"==":"org.bukkit.inventory.ItemStack","v":2580,"type":"BLACK_CONCRETE"},"11":{"==":"org.bukkit.inventory.ItemStack","v":2580,"type":"IRON_SHOVEL"},"33":{"==":"org.bukkit.inventory.ItemStack","v":2580,"type":"REDSTONE_BLOCK"},"12":{"==":"org.bukkit.inventory.ItemStack","v":2580,"type":"MOSSY_COBBLESTONE_WALL"},"34":{"==":"org.bukkit.inventory.ItemStack","v":2580,"type":"SMOOTH_STONE_SLAB"},"13":{"==":"org.bukkit.inventory.ItemStack","v":2580,"type":"SMOOTH_STONE"},"35":{"==":"org.bukkit.inventory.ItemStack","v":2580,"type":"IRON_DOOR","amount":3},"14":{"==":"org.bukkit.inventory.ItemStack","v":2580,"type":"STONE_BRICK_WALL"},"15":{"==":"org.bukkit.inventory.ItemStack","v":2580,"type":"FARMLAND"},"16":{"==":"org.bukkit.inventory.ItemStack","v":2580,"type":"OAK_FENCE"},"17":{"==":"org.bukkit.inventory.ItemStack","v":2580,"type":"DIAMOND_HOE"},"18":{"==":"org.bukkit.inventory.ItemStack","v":2580,"type":"WATER_BUCKET"},"19":{"==":"org.bukkit.inventory.ItemStack","v":2580,"type":"WOODEN_AXE"},"0":{"==":"org.bukkit.inventory.ItemStack","v":2580,"type":"COMMAND_BLOCK"},"1":{"==":"org.bukkit.inventory.ItemStack","v":2580,"type":"WOODEN_AXE"},"2":{"==":"org.bukkit.inventory.ItemStack","v":2580,"type":"WATER_BUCKET"},"4":{"==":"org.bukkit.inventory.ItemStack","v":2580,"type":"CHAIN"},"5":{"==":"org.bukkit.inventory.ItemStack","v":2580,"type":"BIRCH_SIGN","amount":2},"6":{"==":"org.bukkit.inventory.ItemStack","v":2580,"type":"DARK_OAK_FENCE"},"7":{"==":"org.bukkit.inventory.ItemStack","v":2580,"type":"BARRIER"},"8":{"==":"org.bukkit.inventory.ItemStack","v":2580,"type":"CONDUIT"},"9":{"==":"org.bukkit.inventory.ItemStack","v":2580,"type":"WATER_BUCKET"},"20":{"==":"org.bukkit.inventory.ItemStack","v":2580,"type":"WOODEN_AXE"},"21":{"==":"org.bukkit.inventory.ItemStack","v":2580,"type":"WOODEN_AXE"}},"stats":{"ex":"0.0","ma":"300","fl":"20","el":"0","hp":"20.0","xp":"0.42857143","txp":"3","fd":"0.0","ft":"-20","sa":"5.0","ra":"300"}}}